[
    {
        "class": "PESSOA",
        "entity": "Ahasverus",
        "sentence": "Ahasverus e o Gênio Castro Alves",
        "start_char": 0,
        "end_char": 9,
        "excerpt": "Ahasverus e o Gênio Castro Alves Ao poeta e amigo J. Felizardo Júnior Sabes quem foi Ahasverus? ...  o precito, O mísero Judeu, que tinha escrito Na fronte o selo atroz!",
        "gender": "male",
        "pch_occurrences": {
            "testa": {
                "syns": [
                    "fronte",
                    "testas",
                    "frontes"
                ],
                "occurrences": [
                    "fronte"
                ],
                "occurrences_n": 1
            }
        },
        "dependencies": [
            {
                "head": "Ahasverus",
                "child": "o Gênio",
                "dep_h": "ROOT",
                "pos_h": "PROPN",
                "lemma_h": "Ahasverus",
                "dep_c": "conj",
                "pos_c": "PROPN",
                "lemma_c": "Gênio",
                "categories": [],
                "pch_dependencies": []
            },
            {
                "head": "o Gênio",
                "child": "Ahasverus",
                "dep_h": "conj",
                "pos_h": "PROPN",
                "lemma_h": "Gênio",
                "dep_c": "ROOT",
                "pos_c": "PROPN",
                "lemma_c": "Ahasverus",
                "categories": [],
                "pch_dependencies": []
            },
            {
                "head": "Castro",
                "child": "Ahasverus",
                "dep_h": "flat:name",
                "pos_h": "PROPN",
                "lemma_h": "Castro",
                "dep_c": "ROOT",
                "pos_c": "PROPN",
                "lemma_c": "Ahasverus",
                "categories": [],
                "pch_dependencies": []
            },
            {
                "head": "Alves",
                "child": "Ahasverus",
                "dep_h": "flat:name",
                "pos_h": "PROPN",
                "lemma_h": "Alves",
                "dep_c": "ROOT",
                "pos_c": "PROPN",
                "lemma_c": "Ahasverus",
                "categories": [],
                "pch_dependencies": []
            },
            {
                "head": "poeta",
                "child": "Ahasverus",
                "dep_h": "nmod",
                "pos_h": "NOUN",
                "lemma_h": "poeta",
                "dep_c": "ROOT",
                "pos_c": "PROPN",
                "lemma_c": "Ahasverus",
                "categories": [
                    "social"
                ],
                "pch_dependencies": []
            },
            {
                "head": "J. Felizardo Júnior Sabes",
                "child": "Ahasverus",
                "dep_h": "appos",
                "pos_h": "PROPN",
                "lemma_h": "J.",
                "dep_c": "ROOT",
                "pos_c": "PROPN",
                "lemma_c": "Ahasverus",
                "categories": [],
                "pch_dependencies": []
            },
            {
                "head": "Ahasverus",
                "child": "poeta",
                "dep_h": "ROOT",
                "pos_h": "PROPN",
                "lemma_h": "Ahasverus",
                "dep_c": "nmod",
                "pos_c": "NOUN",
                "lemma_c": "poeta",
                "categories": [
                    "social"
                ],
                "pch_dependencies": []
            }
        ]
    },
    {
        "class": "PESSOA",
        "entity": "Gênio Castro Alves",
        "sentence": "Ahasverus e o Gênio Castro Alves",
        "start_char": 14,
        "end_char": 32,
        "excerpt": "Ahasverus e o Gênio Castro Alves Ao poeta e amigo J. Felizardo Júnior Sabes quem foi Ahasverus? ...  o precito, O mísero Judeu, que tinha escrito Na fronte o selo atroz!",
        "gender": "male",
        "pch_occurrences": {
            "testa": {
                "syns": [
                    "fronte",
                    "testas",
                    "frontes"
                ],
                "occurrences": [
                    "fronte"
                ],
                "occurrences_n": 1
            }
        },
        "dependencies": []
    },
    {
        "class": "PESSOA",
        "entity": "J . Felizardo Júnior",
        "sentence": "Ao poeta e amigo J. Felizardo Júnior Sabes quem foi Ahasverus?",
        "start_char": 32,
        "end_char": 52,
        "excerpt": "Ahasverus e o Gênio Castro Alves Ao poeta e amigo J. Felizardo Júnior Sabes quem foi Ahasverus? ...  o precito, O mísero Judeu, que tinha escrito Na fronte o selo atroz!",
        "gender": "unknown",
        "pch_occurrences": {
            "testa": {
                "syns": [
                    "fronte",
                    "testas",
                    "frontes"
                ],
                "occurrences": [
                    "fronte"
                ],
                "occurrences_n": 1
            }
        },
        "dependencies": []
    },
    {
        "class": "PESSOA",
        "entity": "Ahasverus",
        "sentence": "Ao poeta e amigo J. Felizardo Júnior Sabes quem foi Ahasverus?",
        "start_char": 85,
        "end_char": 94,
        "excerpt": "Ahasverus e o Gênio Castro Alves Ao poeta e amigo J. Felizardo Júnior Sabes quem foi Ahasverus? ...  o precito, O mísero Judeu, que tinha escrito Na fronte o selo atroz!",
        "gender": "male",
        "pch_occurrences": {
            "testa": {
                "syns": [
                    "fronte",
                    "testas",
                    "frontes"
                ],
                "occurrences": [
                    "fronte"
                ],
                "occurrences_n": 1
            }
        },
        "dependencies": [
            {
                "head": "Ahasverus",
                "child": "o Gênio",
                "dep_h": "ROOT",
                "pos_h": "PROPN",
                "lemma_h": "Ahasverus",
                "dep_c": "conj",
                "pos_c": "PROPN",
                "lemma_c": "Gênio",
                "categories": [],
                "pch_dependencies": []
            },
            {
                "head": "o Gênio",
                "child": "Ahasverus",
                "dep_h": "conj",
                "pos_h": "PROPN",
                "lemma_h": "Gênio",
                "dep_c": "ROOT",
                "pos_c": "PROPN",
                "lemma_c": "Ahasverus",
                "categories": [],
                "pch_dependencies": []
            },
            {
                "head": "Castro",
                "child": "Ahasverus",
                "dep_h": "flat:name",
                "pos_h": "PROPN",
                "lemma_h": "Castro",
                "dep_c": "ROOT",
                "pos_c": "PROPN",
                "lemma_c": "Ahasverus",
                "categories": [],
                "pch_dependencies": []
            },
            {
                "head": "Alves",
                "child": "Ahasverus",
                "dep_h": "flat:name",
                "pos_h": "PROPN",
                "lemma_h": "Alves",
                "dep_c": "ROOT",
                "pos_c": "PROPN",
                "lemma_c": "Ahasverus",
                "categories": [],
                "pch_dependencies": []
            },
            {
                "head": "poeta",
                "child": "Ahasverus",
                "dep_h": "nmod",
                "pos_h": "NOUN",
                "lemma_h": "poeta",
                "dep_c": "ROOT",
                "pos_c": "PROPN",
                "lemma_c": "Ahasverus",
                "categories": [
                    "social"
                ],
                "pch_dependencies": []
            },
            {
                "head": "J. Felizardo Júnior Sabes",
                "child": "Ahasverus",
                "dep_h": "appos",
                "pos_h": "PROPN",
                "lemma_h": "J.",
                "dep_c": "ROOT",
                "pos_c": "PROPN",
                "lemma_c": "Ahasverus",
                "categories": [],
                "pch_dependencies": []
            },
            {
                "head": "Ahasverus",
                "child": "poeta",
                "dep_h": "ROOT",
                "pos_h": "PROPN",
                "lemma_h": "Ahasverus",
                "dep_c": "nmod",
                "pos_c": "NOUN",
                "lemma_c": "poeta",
                "categories": [
                    "social"
                ],
                "pch_dependencies": []
            }
        ]
    },
    {
        "class": "PESSOA",
        "entity": "O mísero Judeu",
        "sentence": "...  o precito, O mísero Judeu, que tinha escrito Na fronte o selo atroz!",
        "start_char": 112,
        "end_char": 126,
        "excerpt": "Ahasverus e o Gênio Castro Alves Ao poeta e amigo J. Felizardo Júnior Sabes quem foi Ahasverus? ...  o precito, O mísero Judeu, que tinha escrito Na fronte o selo atroz!",
        "gender": "male",
        "pch_occurrences": {
            "testa": {
                "syns": [
                    "fronte",
                    "testas",
                    "frontes"
                ],
                "occurrences": [
                    "fronte"
                ],
                "occurrences_n": 1
            }
        },
        "dependencies": [
            {
                "head": "...  o precito",
                "child": "O mísero Judeu, que tinha escrito",
                "dep_h": "ROOT",
                "pos_h": "NOUN",
                "lemma_h": "precito",
                "dep_c": "appos",
                "pos_c": "NOUN",
                "lemma_c": "mísero",
                "categories": [
                    "social"
                ],
                "pch_dependencies": []
            },
            {
                "head": "O mísero Judeu, que tinha escrito",
                "child": "...  o precito",
                "dep_h": "appos",
                "pos_h": "NOUN",
                "lemma_h": "mísero",
                "dep_c": "ROOT",
                "pos_c": "NOUN",
                "lemma_c": "precito",
                "categories": [
                    "social"
                ],
                "pch_dependencies": []
            }
        ]
    },
    {
        "class": "PESSOA",
        "entity": "o forasteiro",
        "sentence": "o forasteiro Não teve onde... pousar.",
        "start_char": 333,
        "end_char": 345,
        "excerpt": "Misérrimo! Correu o mundo inteiro, E no mundo tão grande... o forasteiro Não teve onde... pousar.",
        "gender": "male",
        "pch_occurrences": null,
        "dependencies": [
            {
                "head": "teve",
                "child": "o forasteiro",
                "dep_h": "ROOT",
                "pos_h": "VERB",
                "lemma_h": "ter",
                "dep_c": "nsubj",
                "pos_c": "NOUN",
                "lemma_c": "forasteiro",
                "categories": [],
                "pch_dependencies": []
            }
        ]
    },
    {
        "class": "PESSOA",
        "entity": "O deserto",
        "sentence": "O deserto negou-lhe  o grão de areia.",
        "start_char": 405,
        "end_char": 414,
        "excerpt": "o forasteiro Não teve onde... pousar. Co'a mão vazia-viu a terra cheia. O deserto negou-lhe  o grão de areia.",
        "gender": "male",
        "pch_occurrences": {
            "mão": {
                "syns": [
                    "mãos"
                ],
                "occurrences": [
                    "mão"
                ],
                "occurrences_n": 1
            }
        },
        "dependencies": [
            {
                "head": "negou-lhe",
                "child": "O deserto",
                "dep_h": "ROOT",
                "pos_h": "VERB",
                "lemma_h": "negou-lhe",
                "dep_c": "nsubj",
                "pos_c": "NOUN",
                "lemma_c": "deserto",
                "categories": [],
                "pch_dependencies": []
            }
        ]
    },
    {
        "class": "PESSOA",
        "entity": "alfombra",
        "sentence": "A savana sem fim-negou-lhe alfombra.",
        "start_char": 544,
        "end_char": 552,
        "excerpt": "A gota d'água  rejeitou-lhe o mar. D'Asia as florestas-lhe negaram sombra A savana sem fim-negou-lhe alfombra.",
        "gender": "female",
        "pch_occurrences": null,
        "dependencies": [
            {
                "head": "A savana",
                "child": "alfombra",
                "dep_h": "nsubj",
                "pos_h": "NOUN",
                "lemma_h": "savana",
                "dep_c": "ROOT",
                "pos_c": "NOUN",
                "lemma_c": "alfombra",
                "categories": [],
                "pch_dependencies": []
            },
            {
                "head": "fim-negou-lhe",
                "child": "alfombra",
                "dep_h": "nmod",
                "pos_h": "NOUN",
                "lemma_h": "fim-negou-lhe",
                "dep_c": "ROOT",
                "pos_c": "NOUN",
                "lemma_c": "alfombra",
                "categories": [],
                "pch_dependencies": []
            },
            {
                "head": "alfombra",
                "child": "A savana",
                "dep_h": "ROOT",
                "pos_h": "NOUN",
                "lemma_h": "alfombra",
                "dep_c": "nsubj",
                "pos_c": "NOUN",
                "lemma_c": "savana",
                "categories": [],
                "pch_dependencies": []
            }
        ]
    },
    {
        "class": "PESSOA",
        "entity": "O chão",
        "sentence": "O chão negou-lhe o pó!",
        "start_char": 554,
        "end_char": 560,
        "excerpt": "D'Asia as florestas-lhe negaram sombra A savana sem fim-negou-lhe alfombra. O chão negou-lhe o pó!",
        "gender": "male",
        "pch_occurrences": null,
        "dependencies": [
            {
                "head": "negou-lhe",
                "child": "O chão",
                "dep_h": "ROOT",
                "pos_h": "VERB",
                "lemma_h": "negou-lhe",
                "dep_c": "nsubj",
                "pos_c": "NOUN",
                "lemma_c": "chão",
                "categories": [],
                "pch_dependencies": []
            }
        ]
    },
    {
        "class": "PESSOA",
        "entity": "o triste",
        "sentence": "Ninguém lhe abriu a porta de seus lares E o triste seguiu só.",
        "start_char": 661,
        "end_char": 669,
        "excerpt": "...  o precito, O mísero Judeu, que tinha escrito Na fronte o selo atroz! Eterno viajor de eterna senda... Espantado a fugir de tenda em tenda, Fugindo embalde à vingadora voz! Misérrimo! Correu o mundo inteiro, E no mundo tão grande... o forasteiro Não teve onde... pousar. Co'a mão vazia-viu a terra cheia. O deserto negou-lhe  o grão de areia. A gota d'água  rejeitou-lhe o mar. D'Asia as florestas-lhe negaram sombra A savana sem fim-negou-lhe alfombra. O chão negou-lhe o pó! ... Tabas, serralhos, tendas e solares... Ninguém lhe abriu a porta de seus lares E o triste seguiu só.",
        "gender": "male",
        "pch_occurrences": {
            "testa": {
                "syns": [
                    "fronte",
                    "testas",
                    "frontes"
                ],
                "occurrences": [
                    "fronte"
                ],
                "occurrences_n": 1
            },
            "mão": {
                "syns": [
                    "mãos"
                ],
                "occurrences": [
                    "mão"
                ],
                "occurrences_n": 1
            }
        },
        "dependencies": [
            {
                "head": "seguiu",
                "child": "o triste",
                "dep_h": "conj",
                "pos_h": "VERB",
                "lemma_h": "seguir",
                "dep_c": "nsubj",
                "pos_c": "NOUN",
                "lemma_c": "triste",
                "categories": [
                    "emo"
                ],
                "pch_dependencies": []
            }
        ]
    },
    {
        "class": "PESSOA",
        "entity": "povos",
        "sentence": "Viu povos de mil climas, viu mil raças, E não pôde entre tantas populaças",
        "start_char": 685,
        "end_char": 690,
        "excerpt": "Tabas, serralhos, tendas e solares... Ninguém lhe abriu a porta de seus lares E o triste seguiu só. Viu povos de mil climas, viu mil raças, E não pôde entre tantas populaças",
        "gender": "male",
        "pch_occurrences": null,
        "dependencies": [
            {
                "head": "Viu",
                "child": "povos",
                "dep_h": "nsubj",
                "pos_h": "PROPN",
                "lemma_h": "Viu",
                "dep_c": "ROOT",
                "pos_c": "ADJ",
                "lemma_c": "povo",
                "categories": [],
                "pch_dependencies": []
            },
            {
                "head": "mil climas",
                "child": "povos",
                "dep_h": "obl",
                "pos_h": "NOUN",
                "lemma_h": "clima",
                "dep_c": "ROOT",
                "pos_c": "ADJ",
                "lemma_c": "povo",
                "categories": [],
                "pch_dependencies": []
            },
            {
                "head": "mil raças",
                "child": "povos",
                "dep_h": "obj",
                "pos_h": "NOUN",
                "lemma_h": "raça",
                "dep_c": "ROOT",
                "pos_c": "ADJ",
                "lemma_c": "povo",
                "categories": [],
                "pch_dependencies": []
            },
            {
                "head": "tantas populaças",
                "child": "povos",
                "dep_h": "obj",
                "pos_h": "NOUN",
                "lemma_h": "populaça",
                "dep_c": "ROOT",
                "pos_c": "ADJ",
                "lemma_c": "povo",
                "categories": [],
                "pch_dependencies": []
            }
        ]
    },
    {
        "class": "PESSOA",
        "entity": "a virgem do Norte",
        "sentence": "Desde a virgem do Norte à de Sevilhas, Desde a inglesa à crioula das Antilhas Não teve um coração!",
        "start_char": 782,
        "end_char": 799,
        "excerpt": "Viu povos de mil climas, viu mil raças, E não pôde entre tantas populaças Beijar uma só mão... Desde a virgem do Norte à de Sevilhas, Desde a inglesa à crioula das Antilhas Não teve um coração!",
        "gender": "unknown",
        "pch_occurrences": {
            "mão": {
                "syns": [
                    "mãos"
                ],
                "occurrences": [
                    "mão"
                ],
                "occurrences_n": 1
            }
        },
        "dependencies": []
    },
    {
        "class": "PESSOA",
        "entity": "a inglesa",
        "sentence": "Desde a virgem do Norte à de Sevilhas, Desde a inglesa à crioula das Antilhas Não teve um coração!",
        "start_char": 821,
        "end_char": 830,
        "excerpt": "Viu povos de mil climas, viu mil raças, E não pôde entre tantas populaças Beijar uma só mão... Desde a virgem do Norte à de Sevilhas, Desde a inglesa à crioula das Antilhas Não teve um coração!",
        "gender": "female",
        "pch_occurrences": {
            "mão": {
                "syns": [
                    "mãos"
                ],
                "occurrences": [
                    "mão"
                ],
                "occurrences_n": 1
            }
        },
        "dependencies": [
            {
                "head": "a virgem",
                "child": "a inglesa",
                "dep_h": "obl",
                "pos_h": "NOUN",
                "lemma_h": "virgem",
                "dep_c": "nmod",
                "pos_c": "NOUN",
                "lemma_c": "inglesa",
                "categories": [
                    "social"
                ],
                "pch_dependencies": []
            },
            {
                "head": "a inglesa",
                "child": "crioula",
                "dep_h": "nmod",
                "pos_h": "NOUN",
                "lemma_h": "inglesa",
                "dep_c": "nmod",
                "pos_c": "NOUN",
                "lemma_c": "crioula",
                "categories": [],
                "pch_dependencies": []
            },
            {
                "head": "a inglesa",
                "child": "a virgem",
                "dep_h": "nmod",
                "pos_h": "NOUN",
                "lemma_h": "inglesa",
                "dep_c": "obl",
                "pos_c": "NOUN",
                "lemma_c": "virgem",
                "categories": [
                    "social"
                ],
                "pch_dependencies": []
            },
            {
                "head": "crioula",
                "child": "a inglesa",
                "dep_h": "nmod",
                "pos_h": "NOUN",
                "lemma_h": "crioula",
                "dep_c": "nmod",
                "pos_c": "NOUN",
                "lemma_c": "inglesa",
                "categories": [],
                "pch_dependencies": []
            },
            {
                "head": "Antilhas",
                "child": "a inglesa",
                "dep_h": "nmod",
                "pos_h": "PROPN",
                "lemma_h": "Antilhas",
                "dep_c": "nmod",
                "pos_c": "NOUN",
                "lemma_c": "inglesa",
                "categories": [],
                "pch_dependencies": []
            }
        ]
    },
    {
        "class": "PESSOA",
        "entity": "crioula das Antilhas",
        "sentence": "Desde a virgem do Norte à de Sevilhas, Desde a inglesa à crioula das Antilhas Não teve um coração!",
        "start_char": 833,
        "end_char": 853,
        "excerpt": "Viu povos de mil climas, viu mil raças, E não pôde entre tantas populaças Beijar uma só mão... Desde a virgem do Norte à de Sevilhas, Desde a inglesa à crioula das Antilhas Não teve um coração!",
        "gender": "unknown",
        "pch_occurrences": {
            "mão": {
                "syns": [
                    "mãos"
                ],
                "occurrences": [
                    "mão"
                ],
                "occurrences_n": 1
            }
        },
        "dependencies": []
    },
    {
        "class": "PESSOA",
        "entity": "as tribos",
        "sentence": "E as tribos se afastavam E as mulheres tremendo murmuravam Com respeito e pavor.",
        "start_char": 897,
        "end_char": 906,
        "excerpt": "E caminhou! ... E as tribos se afastavam E as mulheres tremendo murmuravam Com respeito e pavor.",
        "gender": "male",
        "pch_occurrences": null,
        "dependencies": [
            {
                "head": "afastavam",
                "child": "as tribos",
                "dep_h": "ROOT",
                "pos_h": "VERB",
                "lemma_h": "afastar",
                "dep_c": "nsubj",
                "pos_c": "NOUN",
                "lemma_c": "tribo",
                "categories": [],
                "pch_dependencies": []
            }
        ]
    },
    {
        "class": "PESSOA",
        "entity": "as mulheres",
        "sentence": "E as tribos se afastavam E as mulheres tremendo murmuravam Com respeito e pavor.",
        "start_char": 922,
        "end_char": 933,
        "excerpt": "E caminhou! ... E as tribos se afastavam E as mulheres tremendo murmuravam Com respeito e pavor.",
        "gender": "female",
        "pch_occurrences": null,
        "dependencies": [
            {
                "head": "tremendo",
                "child": "as mulheres",
                "dep_h": "conj",
                "pos_h": "VERB",
                "lemma_h": "tremer",
                "dep_c": "nsubj",
                "pos_c": "NOUN",
                "lemma_c": "mulher",
                "categories": [
                    "outro"
                ],
                "pch_dependencies": []
            }
        ]
    },
    {
        "class": "PESSOA",
        "entity": "o Hebreu",
        "sentence": "No entanto à noite, se o Hebreu passava, Um murmúrio de inveja se elevava, Desde a flor da campina ao colibri.",
        "start_char": 1089,
        "end_char": 1097,
        "excerpt": "Fazia tremer do vale à serra... Ele que só pedia sobre a terra  Silêncio, paz e amor! No entanto à noite, se o Hebreu passava, Um murmúrio de inveja se elevava, Desde a flor da campina ao colibri.",
        "gender": "male",
        "pch_occurrences": null,
        "dependencies": [
            {
                "head": "passava",
                "child": "o Hebreu",
                "dep_h": "advcl",
                "pos_h": "VERB",
                "lemma_h": "passar",
                "dep_c": "nsubj",
                "pos_c": "PROPN",
                "lemma_c": "Hebreu",
                "categories": [],
                "pch_dependencies": []
            }
        ]
    },
    {
        "class": "PESSOA",
        "entity": "a multidão",
        "sentence": "\"Ele não morre\", a multidão dizia...",
        "start_char": 1194,
        "end_char": 1204,
        "excerpt": "Ele que só pedia sobre a terra  Silêncio, paz e amor! No entanto à noite, se o Hebreu passava, Um murmúrio de inveja se elevava, Desde a flor da campina ao colibri. \"Ele não morre\", a multidão dizia...",
        "gender": "female",
        "pch_occurrences": null,
        "dependencies": [
            {
                "head": "dizia",
                "child": "a multidão",
                "dep_h": "parataxis",
                "pos_h": "VERB",
                "lemma_h": "dizer",
                "dep_c": "nsubj",
                "pos_c": "NOUN",
                "lemma_c": "multidão",
                "categories": [],
                "pch_dependencies": []
            }
        ]
    },
    {
        "class": "PESSOA",
        "entity": "Ahasverus",
        "sentence": "O Gênio é como Ahasverus... solitário A marchar, a marchar no itinerário",
        "start_char": 1284,
        "end_char": 1293,
        "excerpt": "mas nunca vivi! \" O Gênio é como Ahasverus... solitário A marchar, a marchar no itinerário",
        "gender": "male",
        "pch_occurrences": null,
        "dependencies": [
            {
                "head": "é",
                "child": "Ahasverus",
                "dep_h": "ROOT",
                "pos_h": "VERB",
                "lemma_h": "ser",
                "dep_c": "obl",
                "pos_c": "PROPN",
                "lemma_c": "Ahasverus",
                "categories": [],
                "pch_dependencies": []
            }
        ]
    },
    {
        "class": "PESSOA",
        "entity": "os invejosos",
        "sentence": "a invejar os invejosos.",
        "start_char": 1384,
        "end_char": 1396,
        "excerpt": "Sem termo do existir. Invejado! a invejar os invejosos.",
        "gender": "male",
        "pch_occurrences": null,
        "dependencies": [
            {
                "head": "invejar",
                "child": "os invejosos",
                "dep_h": "xcomp",
                "pos_h": "VERB",
                "lemma_h": "invejar",
                "dep_c": "obj",
                "pos_c": "NOUN",
                "lemma_c": "invejoso",
                "categories": [
                    "outro",
                    "carater_emo"
                ],
                "pch_dependencies": []
            }
        ]
    },
    {
        "class": "PESSOA",
        "entity": "amigo",
        "sentence": "Pede u'a mão de amigo-dão-lhe palmas:",
        "start_char": 1495,
        "end_char": 1500,
        "excerpt": "E sempre a caminhar... sempre a seguir... Pede u'a mão de amigo-dão-lhe palmas:",
        "gender": "male",
        "pch_occurrences": {
            "mão": {
                "syns": [
                    "mãos"
                ],
                "occurrences": [
                    "mão"
                ],
                "occurrences_n": 1
            }
        },
        "dependencies": [
            {
                "head": "mão",
                "child": "amigo-dão-lhe",
                "dep_h": "obj",
                "pos_h": "NOUN",
                "lemma_h": "mão",
                "dep_c": "nmod",
                "pos_c": "PROPN",
                "lemma_c": "amigo-dão-lhe",
                "categories": [],
                "pch_dependencies": []
            },
            {
                "head": "amigo-dão-lhe",
                "child": "mão",
                "dep_h": "nmod",
                "pos_h": "PROPN",
                "lemma_h": "amigo-dão-lhe",
                "dep_c": "obj",
                "pos_c": "NOUN",
                "lemma_c": "mão",
                "categories": [],
                "pch_dependencies": []
            }
        ]
    },
    {
        "class": "PESSOA",
        "entity": "o desgraçado",
        "sentence": "Responde o desgraçado:-\"Eu não vivi!...",
        "start_char": 1666,
        "end_char": 1678,
        "excerpt": "Mas quando a terra diz: \"Ele não morre\" Responde o desgraçado:-\"Eu não vivi!...",
        "gender": "male",
        "pch_occurrences": null,
        "dependencies": [
            {
                "head": "vivi",
                "child": "o desgraçado:-\"Eu",
                "dep_h": "ccomp",
                "pos_h": "VERB",
                "lemma_h": "viver",
                "dep_c": "nsubj",
                "pos_c": "NOUN",
                "lemma_c": "desgraçado:-\"Eu",
                "categories": [
                    "social"
                ],
                "pch_dependencies": []
            }
        ]
    }
]